{
    "dataList": [
        {
            "id": 0,
            "model": "키호테빛",
            "content": "…….\n"
        },
        {
            "id": 1,
            "model": "키호테빛",
            "content": "Sancho... Eu concebi... uma ideia muito engenhosa..."
        },
        {
            "id": 2,
            "model": "산초피묻음",
            "content": "O que... é dessa vez...?"
        },
        {
            "id": 3,
            "model": "키호테빛",
            "content": "Infelizmente, parece que não temos a força benevolente e mediadora de Bari para acalmar nossas brigas. Então suponho que estamos em um impasse, falta de uma mediação melhor..."
        },
        {
            "id": 4,
            "model": "키호테빛",
            "content": "… do que uma feita à força."
        },
        {
            "id": 5,
            "model": "키호테빛",
            "content": "Vamos testar nossos poderes em um duelo; em um único combate de nossas lanças."
        },
        {
            "id": 6,
            "model": "키호테빛",
            "content": "Vamos, agora. Vamos dar tudo de nós..."
        },
        {
            "id": 7,
            "model": "산초피묻음",
            "content": "……. \n"
        },
        {
            "id": 8,
            "model": "산초피묻음",
            "content": "... Não há outra maneira?"
        },
        {
            "id": 9,
            "model": "키호테빛",
            "content": "Esse impulso, essa minha responsabilidade de perpetuar o festival, de proporcionar à minha Família o que eles anseiam... isso não pode ser interrompido."
        },
        {
            "id": 10,
            "model": "키호테빛",
            "content": "Este carrossel chamado La Manchaland… gira rápido demais para que eu consiga desmontá-lo, mesmo que ele permaneça ancorado no lugar."
        },
        {
            "id": 11,
            "model": "키호테빛",
            "content": "No entanto, se você pudesse destruir o fardo da minha natureza, das minhas responsabilidades... isso não provaria que seu sonho é mais poderoso que o peso do meu dever?"
        },
        {
            "id": 12,
            "model": "키호테빛",
            "content": "Mostre-me. Demonstre diante de mim a força do seu sonho, a grandeza dele."
        },
        {
            "id": 13,
            "model": "산초피묻음",
            "content": "Ainda... tão... ridiculamente juvenil..."
        },
        {
            "id": 14,
            "model": "키호테빛",
            "content": "Quantas vezes devo dizer-lhe que é essa mesma juventude ridícula que dá cor à vida?"
        },
        {
            "id": 15,
            "model": "산초피묻음",
            "content": "…….\n"
        }
    ]
}