{
  "dataList": [
    {
      "id": 0,
      "place": "Backstreets of District 8, Entrance",
      "content": "Estávamos em uma corrida desesperada ..."
    },
    {
      "id": 1,
      "content": "... O tempo todo lutando contra hordas e hordas de inimigos."
    },
    {
      "id": 2,
      "model": "히스클리프",
      "content": "Oi! O que aconteceu com a 'passagem segura e fácil'?! Explique essa merda!"
    },
    {
      "id": 3,
      "model": "경도",
      "content": "Parece que o semblante radiante do jovem mestre foi dado a conhecer ..."
    },
    {
      "id": 4,
      "model": "이스마엘",
      "content": "Achei que estávamos encontrando uma passagem mais clandestina? Como é que estamos sendo atacados por ainda mais inimigos!?"
    },
    {
      "id": 5,
      "model": "경도",
      "content": "Como eu disse, o jovem mestre está radiante -"
    },
    {
      "id": 6,
      "model": "이스마엘",
      "content": "Pelo menos tente dar um pouco de variação às suas desculpas...!"
    },
    {
      "id": 7,
      "model": "오티스",
      "content": "Não posso dizer tão facilmente que ele está sendo falso, dada a lealdade desarticulada dos inimigos que nos atacam ..."
    },
    {
      "id": 8,
      "content": "Outis brincou com o panfleto na mão, claramente frustrada, mas incapaz de estabelecer algo concreto."
    },
    {
      "id": 9,
      "model": "홍루",
      "content": "Para pessoas sem uma lealdade clara para atacar um membro da família Jia..."
    },
    {
      "id": 10,
      "model": "홍루",
      "content": "Parece que todo mundo nas Backstreets tem ficado muito corajoso enquanto eu estava fora. Naquela época, eu não conseguia nem vislumbrar seus rostos - todos eles estavam de joelhos sempre que passávamos... Ah, que mudança maravilhosa!"
    },
    {
      "id": 11,
      "model": "히스클리프",
      "content": "Oh, enfie essa mudança maravilhosa na sua bunda, seu maldito idiota! Quanto tempo mais até chegarmos lá?!"
    },
    {
      "id": 12,
      "model": "경도",
      "content": "... Meu kezhan está próximo, acalme suas preocupações."
    },
    {
      "id": 13,
      "content": "Nosso guia parece estranhamente mais calmo agora do que no início desta jornada."
    },
    {
      "id": 14,
      "content": "Ele realmente ficou entorpecido com toda a violência tão rápido, ou ...?"
    },
    {
      "id": 15,
      "model": "로쟈",
      "content": "Falando nisso... O que é um 'Kezhan'?"
    },
    {
      "id": 16,
      "model": "파우스트",
      "content": "É um termo comumente usado para se referir a tabernas, pousadas ou locais equivalentes de hospedagem nesta região."
    },
    {
      "id": 17,
      "model": "로쟈",
      "content": "Hospedagem, hein... gostar... um hotel?!"
    },
    {
      "id": 18,
      "model": "로쟈",
      "content": "Fuhu, deve ser bem chique então, hein? Eles servem lanches e bebidas de cortesia como o trem WARP?"
    },
    {
      "id": 19,
      "model": "이스마엘",
      "content": "Não tenho certeza sobre isso, mas parece que os kezhans também servem álcool e comida junto com seus serviços de hospedagem. Talvez possamos fazer uma refeição lá."
    },
    {
      "id": 20,
      "model": "그레고르",
      "content": "E uh, ufa. Espero que não sejamos atacados lá assim?"
    },
    {
      "id": 21,
      "model": "경도",
      "content": "Tabu residencial de não agressão. Quaisquer atos mútuos de violência dentro de um edifício residencial são, dentro desta área e andar específicos de Hongyuan, um tabu."
    },
    {
      "id": 22,
      "model": "이상",
      "content": "Um tabu... podemos ficar tranquilos por dentro, então."
    },
    {
      "id": 23,
      "content": "Vi as sobrancelhas de Fausto se contraírem levemente, como se ela tivesse acabado de ouvir a coisa mais ridícula... mas acho que vou perguntar a ela sobre isso mais tarde."
    },
    {
      "id": 24,
      "model": "그레고르",
      "content": "Ufa, cara. Se é para algum tipo de hierarca familiar ou concurso de seleção de chefes de família, por que eles não poderiam salvar toda essa luta até então...?"
    },
    {
      "id": 25,
      "model": "홍루",
      "content": "Porque seria tarde demais."
    },
    {
      "id": 26,
      "model": "그레고르",
      "content": "Hm...? Tarde como?"
    },
    {
      "id": 27,
      "model": "홍루",
      "content": "Todo candidato a Hiererarca deve ter trazido... tesouros incrivelmente preciosos com eles."
    },
    {
      "id": 28,
      "model": "홍루",
      "content": "Seria bom se eles acreditassem que seu próprio tesouro é o mais precioso de todos, mas..."
    },
    {
      "id": 29,
      "model": "이스마엘",
      "content": "Mas todo mundo vai tentar pegar um ao outro só para ter certeza. Entendo. Apenas no caso de alguém trazer algo ainda melhor do que o seu."
    },
    {
      "id": 30,
      "model": "홍루",
      "content": "E ~ pode muito bem matá-los também, por uma questão de conveniência."
    },
    {
      "id": 31,
      "model": "그레고르",
      "content": "... É assim que as pessoas da sua família pensam? Que tipo de linha de pensamento é essa?"
    },
    {
      "id": 32,
      "model": "홍루",
      "content": "Mas outras famílias não pareciam muito diferentes da minha, fuhu."
    },
    {
      "id": 33,
      "model": "히스클리프",
      "content": "... Droga."
    },
    {
      "id": 34,
      "model": "경도",
      "content": "Minhas mais profundas desculpas por se intrometer nesta conversa tão fascinante. Contudo..."
    },
    {
      "id": 35,
      "model": "경도",
      "content": "... Podemos estar convidando ainda mais problemas ao brincar aqui."
    },
    {
      "id": 36,
      "content": "Com isso, o guia puxou um relógio para verificar a hora."
    },
    {
      "id": 37,
      "model": "경도",
      "content": "... Será... noite em breve."
    }
  ]
}