{
    "dataList": [
        {
            "id": 0,
            "place": "Nest K - LC Branch Interior",
            "model": "단테",
            "content": "<Parece que estamos quase lá.>"
        },
        {
            "id": 1,
            "model": "단테",
            "content": "<Posso sentir o Ramo Dourado ressoando por perto.>"
        },
        {
            "id": 2,
            "model": "파우스트",
            "content": "...Parece que estamos nos aproximando do local alvo."
        },
        {
            "id": 3,
            "model": "동랑",
            "teller": "Dongrang",
            "title": "K Corp. Dept. of Food Resource Development",
            "content": "Isso é bom. As fotos e prêmios que deixei ainda devem estar lá."
        },
        {
            "id": 4,
            "model": "삼조",
            "teller": "Samjo",
            "title": "K Corp. Dept. of Food Resource Development",
            "content": "Documentos de pesquisa confidenciais também, Sr. Dongrang."
        },
        {
            "id": 5,
            "model": "이상",
            "content": "…"
        },
        {
            "id": 6,
            "content": "Yi Sang pega uma ampola que Shrenne deixou cair do chão e a examina cuidadosamente."
        },
        {
            "id": 7,
            "model": "동랑",
            "teller": "Dongrang",
            "title": "K Corp. Dept. of Food Resource Development",
            "content": "Que gentil da sua parte. Você não precisava pegá-lo."
        },
        {
            "id": 8,
            "model": "이상",
            "content": "...É a mesma coisa."
        },
        {
            "id": 9,
            "model": "이상",
            "content": "Esta ampola de regeneração..."
        },
        {
            "id": 10,
            "model": "이상",
            "content": "Seu número obedece à mesma regra das \"ampolas de decaimento\" que foram administradas à força à Srta. Ishmael na briga anterior entre os brigões da K Corp e as máquinas invasoras."
        },
        {
            "id": 11,
            "model": "삼조",
            "teller": "Samjo",
            "title": "K Corp. Dept. of Food Resource Development",
            "content": "Isso é o que se chama de código serial. É uma sequência única de números para categorizar ampolas. As que começam com \"O\" são originais. Espere, por que estou explicando isso de novo?"
        },
        {
            "id": 12,
            "model": "이상",
            "content": "Original... Idêntica à \"ampola de decadência\" injetada na Srta. Ishmael... Então isso sugere que sua essência não era diferente daquela da ampola de regeneração."
        },
        {
            "id": 13,
            "model": "동랑",
            "teller": "Dongrang",
            "title": "K Corp. Dept. of Food Resource Development",
            "content": "Esta série de ampolas de regeneração é, bem, como eu digo... É uma solução não diluída. Não é exatamente como as disponíveis comercialmente."
        },
        {
            "id": 14,
            "model": "이상",
            "content": "…"
        },
        {
            "id": 15,
            "model": "동랑",
            "teller": "Dongrang",
            "title": "K Corp. Dept. of Food Resource Development",
            "content": "O que você está pensando agora?"
        },
        {
            "id": 16,
            "model": "이상",
            "content": "Nada."
        },
        {
            "id": 17,
            "model": "동랑",
            "teller": "Dongrang",
            "title": "K Corp. Dept. of Food Resource Development",
            "content": "Quando você me reconheceu pela primeira vez?"
        },
        {
            "id": 18,
            "model": "이상",
            "content": "Já que você nos mostrou as galinhas em cativeiro."
        },
        {
            "id": 19,
            "model": "이상",
            "content": "Teria sido suficiente dar aos seus visitantes um passeio rápido, mas você insistiu em mostrar seu laboratório pessoal..."
        },
        {
            "id": 20,
            "model": "동랑",
            "teller": "Dongrang",
            "title": "K Corp. Dept. of Food Resource Development",
            "content": "Você está certo. Não sei sobre os outros, mas eu queria que você visse a prova demonstrável do meu sucesso."
        },
        {
            "id": 21,
            "model": "동랑",
            "teller": "Dongrang",
            "title": "K Corp. Dept. of Food Resource Development",
            "content": "Ainda estou triste, no entanto. Você provavelmente teve bastante tempo para expressar sua alegria de se reunir com esse seu velho amigo."
        },
        {
            "id": 22,
            "model": "이상",
            "content": "Penso que não tenho mais companheiros ao meu lado."
        },
        {
            "id": 23,
            "model": "동랑",
            "teller": "Dongrang",
            "title": "K Corp. Dept. of Food Resource Development",
            "content": "Você não mudou."
        },
        {
            "id": 24,
            "model": "동랑",
            "teller": "Dongrang",
            "title": "K Corp. Dept. of Food Resource Development",
            "content": "Você sempre gostou de guardar coisas preciosas em garrafas e observá-las."
        },
        {
            "id": 25,
            "model": "이상",
            "content": "E você tinha a intenção de liberá-los e mostrá-los."
        },
        {
            "id": 26,
            "model": "돈키호테",
            "content": "Você disse \"companheiros\"? Devo dizer, Yi Sang, que muitas reuniões com seus companheiros o aguardam nesta jornada!"
        },
        {
            "id": 27,
            "model": "돈키호테",
            "content": "Em uma expedição passada, o, err... alguém usando óculos escuros te confrontou!"
        },
        {
            "id": 28,
            "model": "동랑",
            "teller": "Dongrang",
            "title": "K Corp. Dept. of Food Resource Development",
            "content": "…"
        },
        {
            "id": 29,
            "model": "동랑",
            "teller": "Dongrang",
            "title": "K Corp. Dept. of Food Resource Development",
            "content": "Aha. Então você já teve uma reunião para comemorar. Não é de se espantar que você esteja tão distante de mim."
        },
        {
            "id": 30,
            "model": "동랑",
            "teller": "Dongrang",
            "title": "K Corp. Dept. of Food Resource Development",
            "content": "Mas que preocupante para você."
        },
        {
            "id": 31,
            "model": "동랑",
            "teller": "Dongrang",
            "title": "K Corp. Dept. of Food Resource Development",
            "content": "Parece que você terá que enfrentar outro."
        },
        {
            "id": 32,
            "model": "단테",
            "content": "<O que você quer dizer?>"
        },
        {
            "id": 33,
            "model": "동랑",
            "teller": "Dongrang",
            "title": "K Corp. Dept. of Food Resource Development",
            "content": "Achei que todos tinham escapado graças à delação de Shrenne..."
        },
        {
            "id": 34,
            "model": "동랑",
            "teller": "Dongrang",
            "title": "K Corp. Dept. of Food Resource Development",
            "content": "Mas suponho que não foi esse o caso."
        },
        {
            "id": 35,
            "content": "Alguém entra, exalando um cheiro sufocante e forte de flores."
        },
        {
            "id": 36,
            "content": "Segurando um galho dourado brilhante na mão, um objeto que agora me é familiar."
        },
        {
            "id": 37,
            "content": "Ela tinha uma fotografia monocromática gasta na outra mão."
        },
        {
            "id": 38,
            "model": "동백",
            "teller": "???",
            "title": "???",
            "content": "É uma bela fotografia. Apenas uma desta foto permanece neste mundo agora."
        },
        {
            "id": 39,
            "model": "동랑",
            "teller": "Dongrang",
            "title": "K Corp. Dept. of Food Resource Development",
            "content": "Tantos velhos amigos e nenhum que me recebesse com alegria."
        },
        {
            "id": 40,
            "model": "동랑",
            "teller": "Dongrang",
            "title": "K Corp. Dept. of Food Resource Development",
            "content": "Você não vai me devolver essa foto? Pode não parecer, mas é um tesouro muito estimado meu."
        },
        {
            "id": 41,
            "model": "삼조",
            "teller": "Samjo",
            "title": "K Corp. Dept. of Food Resource Development",
            "content": "Sr. Dongrang, você não deveria chegar perto dela! É perigoso!"
        },
        {
            "id": 42,
            "model": "오티스",
            "content": "Todas as tropas, não se aproximem dela descuidadamente! O Ramo Dourado pode ser destruído..."
        },
        {
            "id": 43,
            "model": "뫼르소",
            "content": "Eu concordo com isso."
        },
        {
            "id": 44,
            "model": "파우스트",
            "content": "Fausto descobrirá uma maneira de recuperá-lo rapidamente."
        },
        {
            "id": 45,
            "model": "히스클리프",
            "content": "Tch, por que continuamos a ter problemas que uma boa surra não resolve! Isso é muito irritante..."
        },
        {
            "id": 46,
            "content": "Todos gritam e berram com seus próprios objetivos em mente."
        },
        {
            "id": 47,
            "content": "Apesar do barulho, a pessoa com o Ramo Dourado caminha firmemente nesta direção."
        },
        {
            "id": 48,
            "content": "No entanto, em vez de ir para Dongrang..."
        },
        {
            "id": 49,
            "model": "동백",
            "teller": "???",
            "title": "???",
            "content": "Aquele cheiro picante e perfumado me fez sentir como se o chão estivesse afundando."
        },
        {
            "id": 50,
            "model": "이상",
            "content": "…!"
        },
        {
            "id": 51,
            "content": "Ela mergulhou o Ramo Dourado em sua mão no peito de Yi Sang..."
        },
        {
            "id": 52,
            "content": "E Yi Sang cai no chão."
        },
        {
            "id": 53,
            "model": "동백",
            "teller": "???",
            "title": "???",
            "content": "Eu... não pensei que você acabaria escolhendo ele diante dos meus olhos."
        },
        {
            "id": 54,
            "model": "단테",
            "content": "<Yi Sang!>"
        },
        {
            "id": 55,
            "model": "동백",
            "teller": "???",
            "title": "???",
            "content": "Você pode ter isso de volta."
        },
        {
            "id": 56,
            "model": "동백",
            "teller": "Dongbaek",
            "title": "???",
            "content": "Uma fotografia nada mais é do que um momento empalhado."
        },
        {
            "id": 57,
            "content": "Mesmo encharcado de sangue, o Ramo Dourado ainda brilha."
        },
        {
            "id": 58,
            "content": "Contrastando com o brilho dourado..."
        },
        {
            "id": 59,
            "content": "A desbotada fotografia monocromática cai lentamente no chão."
        }
    ]
}