{
    "dataList": [
        {
            "id": "1",
            "content": "Custa Módulos Encefalinas para reivindicar recompensas após completar uma expedição na Masmorra dos Espelhos."
        },
        {
            "id": "2",
            "content": "Cada habilidade consiste em pelo menos 1 moeda."
        },
        {
            "id": "3",
            "content": "O poder de uma moeda pode aumentar ou diminuir dependendo da face em que ela cai."
        },
        {
            "id": "4",
            "content": "As faces das moedas também afetam a ativação de certos efeitos de habilidades."
        },
        {
            "id": "5",
            "content": "As unidades podem entrar em estado de Pânico quando sua Sanidade fica abaixo de um certo limite."
        },
        {
            "id": "6",
            "content": "Pecadores com baixa Sanidade serão corroídos pelo E.G.O."
        },
        {
            "id": "7",
            "content": "Pecadores Corroídos atacarão indiscriminadamente, então tome cuidado."
        },
        {
            "id": "8",
            "content": "A potência de um efeito de status indica quanto dano ele causará."
        },
        {
            "id": "9",
            "content": "Após o uso, as habilidades são convertidas em recursos E.G.O correspondentes à sua Afinidade com o Pecado."
        },
        {
            "id": "10",
            "content": "Derrotar uma Anormalidade várias vezes aumenta seu Nível de Observação, permitindo que você cause mais dano a ela em encontros futuros."
        },
        {
            "id": "11",
            "content": "Habilidades que exigem recursos serão canceladas se o personagem não tiver a quantidade necessária."
        },
        {
            "id": "12",
            "content": "A velocidade é determinada aleatoriamente dentro de um determinado intervalo a cada turno."
        },
        {
            "id": "13",
            "content": "A velocidade determina a formação das unidades em combate."
        },
        {
            "id": "14",
            "content": "No início da batalha, seus personagens assumem as Resistências ao Pecado do E.G.O de menor grau que eles equiparam."
        },
        {
            "id": "15",
            "content": "Depois que um Pecador usa E.G.O, suas Resistências ao Pecado são atualizadas; no entanto, quaisquer valores que seriam reduzidos permanecerão como estavam."
        },
        {
            "id": "16",
            "content": "Uma habilidade de Defesa gerada preencherá o espaço de habilidade inferior do Pecador, substituindo a habilidade atual ou E.G.O."
        },
        {
            "id": "17",
            "content": "Cancelar o E.G.O antes de usá-lo retornará seus recursos."
        },
        {
            "id": "18",
            "content": "Se 2 ou mais habilidades do mesmo Pecado estiverem em sequência, a Ressonância do Pecado será ativada, fortalecendo seus ataques."
        },
        {
            "id": "19",
            "content": "Se 3 ou mais habilidades do mesmo Pecado estiverem em sucessão direta, a Ressonância Absoluta será ativada, fortalecendo MUITO seus ataques."
        },
        {
            "id": "20",
            "content": "Quanto mais longo for o Clash, maior será o dano final do vencedor."
        },
        {
            "id": "21",
            "content": "Quando a saúde de um personagem cai abaixo do Limiar de Cambaleio, ele se torna vulnerável a todos os ataques e não pode agir até o final do turno seguinte."
        },
        {
            "id": "22",
            "content": "Em Masmorras, você pode se curar e salvar seu progresso em Pontos de Verificação."
        },
        {
            "id": "23",
            "content": "Cada Identidade tem uma Passiva de Combate e uma Passiva de Suporte."
        },
        {
            "id": "24",
            "content": "Identidades que participam do combate usam Passivas de Combate."
        },
        {
            "id": "25",
            "content": "Pecadores que não estão participando diretamente da batalha fornecerão ajuda com suas Passivas de Suporte."
        },
        {
            "id": "26",
            "content": "As partes de uma anormalidade podem ter resistências e comportamentos diferentes."
        },
        {
            "id": "27",
            "content": "Ao confrontar Anormalidades em Encontros Focados, você pode se deparar com situações que exigem que você faça uma escolha; dependendo do resultado, você pode receber vários efeitos ou até mesmo Presentes E.G.O."
        },
        {
            "id": "28",
            "content": "Ainda é possível passar no teste mesmo sem o Pecado necessário."
        },
        {
            "id": "29",
            "content": "Você pode obter Presentes E.G.O em testes e batalhas conforme avança em uma Masmorra."
        },
        {
            "id": "30",
            "content": "Quando um inimigo fica sem Sanidade e entra em Pânico, ele sofre efeitos negativos."
        },
        {
            "id": "31",
            "content": "Se o HP de um personagem Staggered cair abaixo do próximo Stagger Threshold, ele sofrerá dano extra."
        },
        {
            "id": "32",
            "content": "A contagem de um efeito de status indica quanto tempo ele durará ou quantas vezes ele será ativado durante o combate."
        },
        {
            "id": "33",
            "content": "As habilidades E.G.O são colocadas na parte inferior da coluna de um Pecador."
        },
        {
            "id": "34",
            "content": "Os confrontos ocorrem quando duas Habilidades de Ataque têm como alvo uma a outra."
        },
        {
            "id": "34",
            "content": "Passivas de Combate e Passivas de Suporte exigem que certas Afinidades de Pecado sejam encadeadas ou que seus recursos sejam possuídos para serem ativadas."
        }
    ]
}