{
  "dataList": [
    {
      "id": "ycgd_stagebutton_not_clear",
      "content": "Limpe 5.5-12 para desbloquear"
    },
    {
      "id": "ycgd_stagebutton_normal",
      "content": "Estágios"
    },
    {
      "id": "ycgd_stagebutton_end_event",
      "content": "Evento fechado"
    },
    {
      "id": "ycgd_storybutton_before_start",
      "content": "[[Size de tag-size]] Veja o 1º estágio da história do evento para desbloquear [[size de tag-size]]"
    },
    {
      "id": "ycgd_storybutton_normal",
      "content": "Para o teatro"
    },
    {
      "id": "ycgd_rewardShopButton",
      "content": "Troca de recompensa"
    },
    {
      "id": "ycgd_scrap_guide_title",
      "content": "Guia de moeda de eventos"
    },
    {
      "id": "ycgd_scrap_guide_desc",
      "content": "Raramente, você pode obter [[colorido de tag]] [[suporte]] [[colorido de tag]] de estágios de compensação de eventos, estágios principais da história ou masmorras de espelho.\n\n[[Tag-Color]] [[Bracket]] [[Tag-Color]] é convertido em 20 [[colorido de tag]] [[suporte]] [[tag-color]]."
    },
    {
      "id": "ycgd_rewardpage_desc",
      "content": "Você pode obter [[Tag-Color]] [[Bracket]] [[Tag-Color]] dos estágios do evento e masmorra.\nVocê também tem uma pequena chance de obter [[colorido de tag]] [[backet]] [[colorido tag]] no processo.\n\n[[Tag-Color]] [[Bracket]] [[Tag-Color]] é imediatamente convertido em 20 [[colorido de tag]] [[bracket]] [[tag-color]] após a aquisição."
    },
    {
      "id": "ycgd_reward_popup_desc",
      "content": "GANHE [[TAG-COLOR]] [[Bracket]] [[Tag-Color]] através dos seguintes métodos:\nA fase de eventos limpa, o espelho Dungeon limpa,\ne o palco principal da história limpa pela primeira vez.\n\nNa [[coloria tag]] [[backet]] [[tag-color]], você pode comprar várias recompensas\nAo gastar [[colorido de tag]] [[backet]] [[tag-color]] você coletou."
    },
    {
      "id": "ycgd_reward_popup_num_of_owned_items",
      "content": "Bosques coletados"
    },
    {
      "id": "ycgd_bonusUI_Title",
      "content": "Ganho"
    },
    {
      "id": "ycgd_bonusUI_Title_contain_false",
      "content": "Não possuía"
    },
    {
      "id": "ycgd_bonusUI_Desc",
      "content": "Durante o período do evento, implantar as seguintes identidades em sua equipe irá\nAumente a quantidade de [[colorido de tag]] [[backet]] [[tag-color]] ganhou.\nVocê pode obter um máximo de [[colorido]] 120%[[colorido de tag]] aumentando a quantidade de moeda de eventos conquistados."
    },
    {
      "id": "ycgd_bonus_popup_title",
      "content": "Unidades de bônus de evento"
    },
    {
      "id": "ycgd_bonus_preview",
      "content": "Unidades de bônus de evento"
    },
    {
      "id": "ycgd_chapter_map_difficulty_ui_9107",
      "content": "NORMAL"
    },
    {
      "id": "ycgd_chapter_map_difficulty_ui_9115",
      "content": "DURO"
    },
    {
      "id": "ycgd_chapter_map_difficulty_ui_unlock_condition",
      "content": "Claro {0}-{1} para desbloquear a dificuldade"
    }
  ]
}