{
  "dataList": [
    {
      "id": 10601,
      "title": "Wuthering Heights"
    },
    {
      "id": 10602,
      "title": "Não há tempo"
    },
    {
      "id": 10603,
      "title": "Não há tempo 2"
    },
    {
      "id": 10604,
      "title": "A carta"
    },
    {
      "id": 10605,
      "title": "Cores"
    },
    {
      "id": 10606,
      "title": "A reforma"
    },
    {
      "id": 10607,
      "title": "O portão da frente"
    },
    {
      "id": 10608,
      "title": "Nelly"
    },
    {
      "id": 10609,
      "title": "Uma recepção quente"
    },
    {
      "id": 10610,
      "title": "Catherine"
    },
    {
      "id": 10611,
      "title": "Butlers"
    },
    {
      "id": 10612,
      "title": "O fantasma"
    },
    {
      "id": 10613,
      "title": "Enigmas"
    },
    {
      "id": 10614,
      "title": "O corredor"
    },
    {
      "id": 10615,
      "title": "O corredor 2"
    },
    {
      "id": 10616,
      "title": "O corredor 3"
    },
    {
      "id": 10617,
      "title": "Os coelhos mortos"
    },
    {
      "id": 10618,
      "title": "Os coelhos mortos 2"
    },
    {
      "id": 10619,
      "title": "O diário"
    },
    {
      "id": 10620,
      "title": "O diário 2"
    },
    {
      "id": 10621,
      "title": "A lareira"
    }
  ]
}