{
    "dataList": [
        {
            "id": 9101701,
            "name": "Collective Achievement",
            "desc": "Se o alvo for escalonado pelo ataque desta unidade ou[VibrationExplosion], todos os aliados curam 10 sp"
        },
        {
            "id": 9014201,
            "name": "Emergency Time Loan",
            "desc": "Turn Start: Se esta unidade estiver escalonada, ganhe +3[TimeRentalTwo]Contar."
        },
        {
            "id": 9014202,
            "name": "Golden Time I",
            "desc": "No final do turno, se o HP estiver entre 16% e 20%, curar instantaneamente até 60% do HP máximo e se recuperar de escalonamento. (Uma vez Max)"
        },
        {
            "id": 9014203,
            "name": "Time Recoil I",
            "desc": "Depois de ativar o tempo de ouro, ganhe 2[Vulnerable]No próximo turno, começo"
        },
        {
            "id": 9014204,
            "name": "Ready to Borrow Time",
            "desc": "Vire início: se esta unidade não tiver[TimeRentalTwo], ganhe +5 contagem de tremores"
        },
        {
            "id": 9014301,
            "name": "Golden Time II",
            "desc": "No final do turno, se o HP estiver entre 10% e 20%, curar instantaneamente até 80% do máximo de HP e se recuperar de escalonamento. (Uma vez Max)"
        },
        {
            "id": 9014302,
            "name": "Time Recoil II",
            "desc": "Depois de ativar o tempo de ouro, ganhe 3[Vulnerable]No próximo turno, começo"
        },
        {
            "id": 9014303,
            "name": "Borrow Time",
            "desc": "Encontro Início: Ganhe +4[TimeRentalTwo]Contar"
        }
    ]
}