{
  "dataList": [
    {
      "id": "get_11209_1",
      "desc": "Aquisição de identidade",
      "dlg": "Você também está aqui para se juntar à caçada por esse bastardo? Ou você está apenas aqui para ... apreciar essa desolação?"
    },
    {
      "id": "lobby_morning_11209_1",
      "desc": "Saudação matinal",
      "dlg": "Feche a janela, sim? Eu tive o infortúnio de nascer em um corpo que entra em tosse com a menor brisa."
    },
    {
      "id": "lobby_noon_11209_1",
      "desc": "Saudação da tarde",
      "dlg": "Não espere ver o sol tão cedo, desde que você esteja aqui. Ele se esconde para sempre mais além do céu nublado. É tão distante quanto a noção de paz é para nós."
    },
    {
      "id": "lobby_night_11209_1",
      "desc": "Saudação noturna",
      "dlg": "O vendaval apressado me acorda do meu sono já superficial. Talvez meus pesadelos tenham voltado do esquecimento ao rap nas minhas janelas novamente."
    },
    {
      "id": "smalltalk_11209_1",
      "desc": "Conversas #1",
      "dlg": "Ah, é você. Um ... hóspede bastante desagradável me visita de tempos em tempos. Embora eu tenha feito uma aliança com ele, pois não tinha alternativa ... eu sei que ele está sempre pronto para me esfaquear pelas costas."
    },
    {
      "id": "smalltalk_11209_2",
      "desc": "Conversas #2",
      "dlg": "Uma lâmina mais nítida leva a uma mente mais nítida? É uma carga de porcaria. Minha lâmina é mais nítida do que qualquer coisa ... porque paguei um bom dinheiro por isso. Mas ... todas as noites ... toda vez que me mexendo acordado, estou preso em um mundo de dúvida sem fim ... imaginando se tudo isso não havia sido um pesadelo terrível."
    },
    {
      "id": "smalltalk_11209_3",
      "desc": "Conversas #3",
      "dlg": "Você já viu essa mansão? Aquele lugar desolado visitado apenas pelos ventos e raios de Wuthering. Não inspira nada além de desespero ... que é, ironicamente, o que me faz continuar."
    },
    {
      "id": "smalltalk_11209_4",
      "desc": "Chat pós-uptie 1",
      "dlg": "Às vezes, quando vejo uma lápide sem nome ... meu coração começa a correr como se estivesse prestes a explodir. Agora ... você sabe por que isso pode ser?"
    },
    {
      "id": "smalltalk_11209_5",
      "desc": "Chat pós-uptie 2",
      "dlg": "Aquele bastardo cortou deliberadamente apenas um dos meus braços. Eu não escapei; Eu fui libertado. Ele me diz que devemos participar de um jogo de esconde-esconde que não poderíamos quando crianças. Veremos quem caça quem no final."
    },
    {
      "id": "neglect_11209_1",
      "desc": "Parado",
      "dlg": "Não se preocupe. Estou acostumado a ser esquecido."
    },
    {
      "id": "gacksung_11209_1",
      "desc": "Uptying",
      "dlg": "Sim ... já era hora de aguçar a lâmina da minha espada."
    },
    {
      "id": "formation_11209_1",
      "desc": "Implantação",
      "dlg": "Encontramos nossa presa?"
    },
    {
      "id": "battleentry_11209_1",
      "desc": "Entrada no palco",
      "dlg": "Este é o momento da lamentação."
    },
    {
      "id": "battle_select_11209_1",
      "desc": "Visto em batalha",
      "dlg": "Você tem algo a dizer para mim?"
    },
    {
      "id": "battle_endcommand_11209_1",
      "desc": "Ataques iniciando",
      "dlg": "Eu dedico esta lâmina a você."
    },
    {
      "id": "battle_enemy_break_11209_1",
      "desc": "Inimigo cambaleia",
      "dlg": "Espero que você não esperasse encontrar honra nesta batalha."
    },
    {
      "id": "battle_break_11209_1",
      "desc": "Escalonado",
      "dlg": "Se eu caísse aqui ... ele ... zombaria de mim tão selvagem."
    },
    {
      "id": "battle_kill_11209_1",
      "desc": "Inimigo morto",
      "dlg": "Eu atingi, mas um dos seus pontos vitais ..."
    },
    {
      "id": "battle_dead_11209_1",
      "desc": "Morte",
      "dlg": "Ah, a névoa desaparece ... eu finalmente posso ver o rosto daquele que eu tanto desejava ver em meus sonhos ..."
    },
    {
      "id": "choice_success_p_11209_2",
      "desc": "Verifique se passou",
      "dlg": "Comparado ao que eu reduzi no meu caminho, isso foi ... fácil."
    },
    {
      "id": "choice_fail_n_11209_1",
      "desc": "Verifique a falha",
      "dlg": "Ele escorregou minha visão."
    },
    {
      "id": "battle_clear_11209_1",
      "desc": "Victory Cry",
      "dlg": "A batalha final está além ainda. Quase não há tempo para comemorar."
    },
    {
      "id": "battle_clear_ex_11209_1",
      "desc": "Condições extras cumpridas",
      "dlg": "Deixe esta lâmina entrar em seu coração negro."
    },
    {
      "id": "battle_defeat_11209_1",
      "desc": "Derrota lamento",
      "dlg": "Simplesmente não era o tempo."
    }
  ]
}