{
  "dataList": [
    {
      "id": 0,
      "content": "Estamos balançando a cavalo"
    },
    {
      "id": 1,
      "content": "As colinas são verdes"
    },
    {
      "id": 2,
      "content": "E os passarinhos cantam"
    },
    {
      "id": 3,
      "content": "E as rosas são rosa"
    },
    {
      "id": 4,
      "content": "Experiência que nunca tive"
    },
    {
      "id": 5,
      "content": "Estou tão feliz"
    },
    {
      "id": 6,
      "content": "Feliz por fazer parte da sua história"
    },
    {
      "id": 7,
      "content": "Depois de você eu sigo"
    },
    {
      "id": 8,
      "content": "Depois de você eu sigo"
    },
    {
      "id": 9,
      "content": "O mundo que você me mostra amplia meu horizonte"
    },
    {
      "id": 10,
      "content": "Para sempre meu herói"
    },
    {
      "id": 11,
      "content": "Para sempre meu herói"
    },
    {
      "id": 12,
      "content": "Eu sou seu maior fã"
    },
    {
      "id": 13,
      "content": "Eu sou seu maior fã"
    },
    {
      "id": 14,
      "content": "Carrossel"
    },
    {
      "id": 15,
      "content": "Em um círculo eu corro"
    },
    {
      "id": 16,
      "content": "É muito divertido deixar a realidade para trás"
    },
    {
      "id": 17,
      "content": "<style=\"den\">Eu caio a cavalo"
    },
    {
      "id": 18,
      "content": "<style=\"den\">Com minhas pernas aleijadas"
    },
    {
      "id": 19,
      "content": "<style=\"den\">E então começa a chover"
    },
    {
      "id": 20,
      "content": "<style=\"den\">Mostrando-me que é tudo falso"
    },
    {
      "id": 21,
      "content": "<style=\"den\">Gotas de chuva lavam a fachada"
    },
    {
      "id": 22,
      "content": "<style=\"den\">As colinas são pintadas"
    },
    {
      "id": 23,
      "content": "<style=\"den\">Birdies são robóticos"
    },
    {
      "id": 24,
      "content": "<style=\"den\">As rosas são feitas de barro"
    },
    {
      "id": 25,
      "content": "<style=\"den\">Excitação que sinto"
    },
    {
      "id": 26,
      "content": "<style=\"den\">Excitação que sinto"
    },
    {
      "id": 27,
      "content": "<style=\"den\">Devolva-os à prateleira"
    },
    {
      "id": 28,
      "content": "<style=\"den\">Porque agora eu entendo"
    },
    {
      "id": 29,
      "content": "<style=\"den\">Heróis não podem ser reais"
    },
    {
      "id": 30,
      "content": "<style=\"den\">Heróis não podem ser reais"
    },
    {
      "id": 31,
      "content": "<style=\"den\">Eu não era quem eu sou"
    },
    {
      "id": 32,
      "content": "<style=\"den\">Eu não sei quem eu sou"
    },
    {
      "id": 33,
      "content": "<style=\"den\">¿Quem sou eu?"
    },
    {
      "id": 34,
      "content": "<style=\"den\">¿Quem sou eu?"
    },
    {
      "id": 35,
      "content": "<style=\"den\">¿Quem sou eu?"
    },
    {
      "id": 36,
      "content": "Aqui vamos nós, mais uma volta"
    },
    {
      "id": 37,
      "content": "Prêmios para reivindicar"
    },
    {
      "id": 38,
      "content": "Aqui está um sonho para você"
    },
    {
      "id": 39,
      "content": "Aqui está um sonho para mim"
    },
    {
      "id": 40,
      "content": "Os bilhetes dourados na minha mala permanecem inalterados"
    },
    {
      "id": 41,
      "content": "Você não ama a emoção da perseguição?"
    },
    {
      "id": 42,
      "content": "Apenas deixe-me ser seu fã"
    },
    {
      "id": 43,
      "content": "Eu quero ser seu fã"
    },
    {
      "id": 44,
      "content": "Eu ainda sou seu maior fã"
    },
    {
      "id": 45,
      "content": "<style=\"den\">Por que alguns receberam o papel de vilão"
    },
    {
      "id": 46,
      "content": "<style=\"den\">No momento em que foram lançados neste sistema?"
    },
    {
      "id": 47,
      "content": "Levante-se"
    },
    {
      "id": 48,
      "content": "Galope"
    },
    {
      "id": 49,
      "content": "Nada pode ser feito sentindo tanta pena de mim mesmo"
    },
    {
      "id": 50,
      "content": "Herói"
    },
    {
      "id": 51,
      "content": "Em um cavalo de plástico"
    },
    {
      "id": 52,
      "content": "Lutando como se fosse real"
    },
    {
      "id": 53,
      "content": "Com uma espada de papelão"
    },
    {
      "id": 54,
      "content": "Eu sei"
    },
    {
      "id": 55,
      "content": "Bem-sucedido ou não, eu sou quem eu sou"
    },
    {
      "id": 56,
      "content": "Eu sou meu maior fã"
    },
    {
      "id": 57,
      "content": "Eu sou meu maior fã"
    },
    {
      "id": 58,
      "content": "Eu sou meu inimigo e meu amigo"
    },
    {
      "id": 59,
      "content": "Herói"
    },
    {
      "id": 60,
      "content": "Vou provar minha versão de justiça"
    },
    {
      "id": 61,
      "content": "É mais justo que o seu"
    },
    {
      "id": 62,
      "content": "ONU"
    },
    {
      "id": 63,
      "content": "Permanecendo neste palco, eu sou o único"
    },
    {
      "id": 64,
      "content": "Eu sou meu maior fã"
    },
    {
      "id": 65,
      "content": "Eu sou meu maior fã"
    },
    {
      "id": 66,
      "content": "Eu sou meu inimigo e meu amigo"
    }
  ]
}